Metadata-Version: 2.1
Name: jax-dips
Version: 0.2.1
Summary: Differentiable 3D interfacial PDE solvers written in JAX using the Neural Bootstrapping Method.
Home-page: https://github.com/JAX-DIPS/JAX-DIPS
Author: Pouria Mistani & Samira Pakravan
Author-email: p.a.mistani@gmail.com
Maintainer: Pouria Mistani & Samira Pakravan
Maintainer-email: p.a.mistani@gmail.com
License: GNU LESSER GENERAL PUBLIC LICENSE v2.1
Classifier: Development Status :: 3 - Alpha
Classifier: Intended Audience :: Developers
Classifier: Intended Audience :: Financial and Insurance Industry
Classifier: Intended Audience :: Information Technology
Classifier: Intended Audience :: Science/Research
Classifier: License :: OSI Approved :: GNU Lesser General Public License v2 (LGPLv2)
Classifier: Natural Language :: English
Classifier: Programming Language :: Python :: 3
Classifier: Topic :: Scientific/Engineering :: Artificial Intelligence
Classifier: Topic :: Scientific/Engineering :: Bio-Informatics
Classifier: Topic :: Scientific/Engineering :: Mathematics
Classifier: Topic :: Scientific/Engineering :: Physics
Requires-Python: ~=3.8
License-File: LICENSE.md
Requires-Dist: jax
Requires-Dist: dm-haiku (==0.0.9)
Requires-Dist: flax (==0.6.10)
Requires-Dist: optax (==0.1.5)
Requires-Dist: jaxopt
Requires-Dist: cython (==0.29.20)
Requires-Dist: pillow
Requires-Dist: pandas
Requires-Dist: pytest
Requires-Dist: matplotlib
Requires-Dist: meshio[all]
Requires-Dist: gdown
Requires-Dist: warp-lang (==0.9.0)
Requires-Dist: pyexr
Requires-Dist: trimesh (>=3.0)
Requires-Dist: scipy
Requires-Dist: scikit-image
Requires-Dist: six (==1.12.0)
Requires-Dist: moviepy
Requires-Dist: opencv-python
Requires-Dist: plyfile
Requires-Dist: polyscope
Requires-Dist: mesh2sdf
Requires-Dist: hydra-core (==1.3.2)
Requires-Dist: hydra-colorlog
Requires-Dist: black (==23.3.0)
Requires-Dist: flake8 (==6.0.0)
Requires-Dist: isort (==5.12.0)
Requires-Dist: pre-commit (==3.3.2)
Requires-Dist: biopython (==1.79)
Requires-Dist: biopandas (==0.4.1)
Requires-Dist: rdkit-pypi (==2022.3.5)
Requires-Dist: pyevtk
Requires-Dist: jaxlib ; extra == "cuda12_local"
